MANIFEST.in
README.md
setup.py
ots2/__init__.py
ots2/client.py
ots2/connection.py
ots2/error.py
ots2/metadata.py
ots2/protocol.py
ots2/retry.py
ots2/protobuf/__init__.py
ots2/protobuf/decoder.py
ots2/protobuf/encoder.py
ots2/protobuf/ots_protocol_2_pb2.py
ots2/test/__init__.py
ots2/test/mock_connection.py
ots2/test/sdk_mock_unittest.py
ots2/test/sdk_param_unittest.py
warriors/__init__.py
warriors/engine.py
warriors/row.py
warriors/sync.py
warriors/table.py
warriors/test.py
warriors.egg-info/PKG-INFO
warriors.egg-info/SOURCES.txt
warriors.egg-info/dependency_links.txt
warriors.egg-info/top_level.txt