Metadata-Version: 1.0
Name: warriors
Version: 0.2.4
Summary: warriors-python-SDK
Home-page: UNKNOWN
Author: Simon_L.Y.B
Author-email: 1289498399@qq.com
License: MIT
Platform: UNKNOWN
